anygrad/__init__.py
anygrad/version.py
anygrad/autograd/__init__.py
anygrad/autograd/autograd.py
anygrad/autograd/helper/__init__.py
anygrad/autograd/helper/grad_helper.py
anygrad/autograd/helper/graph.py
anygrad/tensor/__init__.py
anygrad/tensor/tensor.py
anygrad/tensor/base/ThHelper.py
anygrad/tensor/base/__init__.py
anygrad/tensor/base/basetensor.py
anygrad/tensor/base/booltensor.py
anygrad/tensor/base/floattensor.py
anygrad/tensor/base/inttensor.py
anygrad/tensor/base/tensor_c.cp311-win32.pyd
anygrad/utils/__init__.py
anygrad/utils/generator.py
anygrad/utils/utils_c.cp311-win32.pyd
anygrad-0.0.4.dist-info/LICENSE
anygrad-0.0.4.dist-info/METADATA
anygrad-0.0.4.dist-info/WHEEL
anygrad-0.0.4.dist-info/top_level.txt
anygrad-0.0.4.dist-info/RECORD
