Metadata-Version: 2.2
Name: anygrad
Version: 0.0.4
Summary: A Tensor module that allows a deep learning framework to switch seamlessly between different engines.
Author: Ruhaan
Author-email: ruhaan123dalal@gmail.com
License: MIT
Classifier: Programming Language :: Python :: 3
Classifier: Operating System :: OS Independent
License-File: LICENSE
Requires-Dist: pybind11
Requires-Dist: numpy
Dynamic: author
Dynamic: author-email
Dynamic: classifier
Dynamic: description
Dynamic: description-content-type
Dynamic: license
Dynamic: requires-dist
Dynamic: summary
